mplite/__init__.py
mplite-1.3.1.data/data/LICENSE
mplite-1.3.1.data/data/README.md
mplite-1.3.1.data/data/requirements.txt
mplite-1.3.1.dist-info/LICENSE
mplite-1.3.1.dist-info/METADATA
mplite-1.3.1.dist-info/WHEEL
mplite-1.3.1.dist-info/top_level.txt
mplite-1.3.1.dist-info/RECORD
